kitx_snowflake-1.1.1.dist-info/METADATA
kitx_snowflake-1.1.1.dist-info/WHEEL
kitx_snowflake/__init__.py
kitx_snowflake/kitx_snowflake.abi3.so
kitx_snowflake-1.1.1.dist-info/RECORD
