Metadata-Version: 2.4
Name: kitx-snowflake
Version: 1.1.1
Classifier: Development Status :: 4 - Beta
Classifier: Programming Language :: Python
Classifier: Programming Language :: Python :: 3.8
Classifier: Programming Language :: Python :: 3.9
Classifier: Programming Language :: Python :: 3.10
Classifier: Programming Language :: Python :: 3.11
Classifier: Programming Language :: Python :: 3.12
Classifier: Programming Language :: Python :: Implementation :: CPython
Classifier: Programming Language :: Python :: Implementation :: PyPy
Summary: kits: kitx-snowflake; snowflake id algorithm; sometimes one millis can’t use up 4096 ID; 雪花id生成器， 每毫秒最大生成4096个id
Keywords: kitx-snowflake,kitx,snowflake
Author-email: kitx <carepsb@gmail.com>
License: MIT
Requires-Python: >=3.7
